HISTORY.rst
README.rst
setup.py
ever2simple/__init__.py
ever2simple/converter.py
ever2simple/core.py
ever2simple.egg-info/PKG-INFO
ever2simple.egg-info/SOURCES.txt
ever2simple.egg-info/dependency_links.txt
ever2simple.egg-info/entry_points.txt
ever2simple.egg-info/not-zip-safe
ever2simple.egg-info/requires.txt
ever2simple.egg-info/top_level.txt