Metadata-Version: 1.0
Name: ever2simple
Version: 1.0a2
Summary: Migrate from evernote to simplenote with markdown formatting
Home-page: http://claytron.com
Author: Clayton Parker
Author-email: robots@claytron.com
License: UNKNOWN
Keywords: note taking migration
Platform: UNKNOWN
